Metadata-Version: 1.0
Name: qrc-build
Version: 0.0.1
Summary: Convert folder to qrc for pyqt
Home-page: http://www.tdace.com
Author: zhangligang
Author-email: 394452216@qq.com
License: UNKNOWN
Platform: UNKNOWN
